{
    "navibar": {
        "jp": {
            "portfolio": "ポートフォリオ",
            "profession": "Web/SE",
            "name": "オルロフ",
            "menu": {
                "about": "紹介",
                "profile": "履歴書",
                "skills": "スキル",
                "apps": "実績"
            } 
        },
        "en": {
            "portfolio": "Portfolio",
            "profession": "Web/SE",
            "name": "Orloff",
            "menu": {
                "about": "About",
                "profile": "Profile",
                "skills": "Experiences",
                "apps": "My apps"
            } 
        },
        "fr": {
            "portfolio": "Portfolio",
            "profession": "Web/SE",
            "name": "Orloff",
            "menu": {
                "about": "About",
                "profile": "Profile",
                "skills": "Skills",
                "apps": "My apps"
            } 
        }
    },
    "about": {
        "jp": {
            "title": "紹介",
            "line1": "オルロフ・ニコラ",
            "line2": "２９歳　フランス人",
            "line3": "",
            "line4": "８年前より日本在住、東京都、埼玉県、大阪府に在住経験あり",
            "line5": "フランスのエクス・マルセイユ大学で「応用言語」を専攻",
            "line6": "英語・日本語・翻訳・国際ビジネスを履修",
            "line7": "１年間上智大学に交換留学",
            "line8": "",
            "line9": "東京でホテルに勤めて言語・コミュニケーションスキルを磨いた。",
            "line10": "その後Web開発を独学で勉強し始め、",
            "line11": "大阪でフロントエンドウェブエンジニアとして勤務し、",
            "line12": "多くのECサイトをコーディング。",
            "line13": "",
            "line14": "現在は新しい技術を身につけたく、",
            "line15": "現在はiOSのアプリ開発（SwiftUI）を勉強中。",
            "line16": "",
            "line17": "趣味は音楽（ベース演奏）・キャンプ・ドライブ・歴史・フランス政治・ガジェット系",
            "line18": "好きなものはコーヒー・日本酒・犬・チョコレート・ゴーヤチャンプル"
        },
        "en": {
            "title": "About me",
            "line1": "My name is Nicolas ORLOFF.",
            "line2": "I am a 29-year-old, from France.",
            "line3": "",
            "line4": "I have been living in Japan for eight years.",
            "line5": "I majored in “Applied Linguistics” at a university in France.",
            "line6": "I studied English, Japanese, and translation.",
            "line7": "I spent one year as an exchange student at Sophia University.",
            "line8": "",
            "line9": "I have been interested in IT for a long time.",
            "line10": "I started studying web development four years ago.",
            "line11": "Three years ago, I changed careers and began working as a front-end web engineer.",
            "line12": "",
            "line13": "Currently, I am studying iOS app development (SwiftUI) to acquire new skills.",
            "line14": "",
            "line15": "",
            "line16": "",
            "line17": "",
            "line18": ""
        },
        "fr": {
            "title": "À propos de moi",
            "line1": "Je m'appelle Nicolas ORLOFF.",
            "line2": "Je suis un Français de 29 ans.",
            "line3": "",
            "line4": "Je vis au Japon depuis huit ans.",
            "line5": "J'ai étudié la “Linguistique appliquée” à l'université en France.",
            "line6": "J'ai étudié l'anglais, le japonais et la traduction.",
            "line7": "J'ai passé un an en échange universitaire à l'Université Sophia.",
            "line8": "",
            "line9": "Je m'intéresse à l'informatique depuis longtemps.",
            "line10": "J'ai commencé à étudier le développement web il y a quatre ans.",
            "line11": "Il y a trois ans, j'ai changé de carrière et commencé à travailler en tant qu'ingénieur web front-end.",
            "line12": "",
            "line13": "Actuellement, j'étudie le développement d'applications iOS (SwiftUI) pour acquérir de nouvelles compétences.",
            "line14": "",
            "line15": "",
            "line16": "",
            "line17": "",
            "line18": ""
        }
    },
    "profile": {
        "jp": {
            "title": "履歴書",
            "work": {
                "title": "職歴",
                "content": "<b>ザ・ノット東京新宿 フロント・販売促進部</b>　2018年～2021年\n受付、日本語／英語での対応、英語教室の講師、パソコン作業\n\n<b>株式会社アプロ総研・エンジニア</b>　2021年〜2024年\nEC用CMS上フロントエンドコーディング（HTML・CSS・Javascript）\nお客様と社内のサイトとドメイン保守\nコーディング案件の見積作成"
            },
            "studies": {
                "title": "学歴",
                "content": "<b>上智大学 (交換留学)</b>　2016年〜2017年\nインテンシブ日本語教室\n\n<b>エクスマルセイユ大学 (フランス) </b>　2013年〜2016年\n応用言語：日本語、英語、翻訳、国際経済"
            },
            "diplomas": {
                "title": "資格",
                "content": "<b>普通自動車運転免許</b>　2024年\n<b>ビジネスマナー研修を受講 (OJT)</b>　2022年　\n<b>日本語能力試験1級 (JLPT N1)</b>　2019年\n<b>TOEIC (スコア：870)</b>　2016年"
            }
        },
        "en": {
            "title": "Profile",
            "work": {
                "title": "Work History",
                "content": "<b>The Knot Tokyo Shinjuku - Sales promotion</b>　2018-2021\nFront Desk, use of Japanese and English, English class teacher, computer tasks\n\n<b>Apro Soken - Engineer</b>　2021-2024\nCoding in HTML, CSS, JS / Website domain management / Quotation for coding projects"
            },
            "studies": {
                "title": "Academic Background",
                "content": "<b>Exchange in Sophia University - Tokyo</b>　2016-2017\nIntensive Japanese class\n\n<b>Aix Marseille University</b>　2013-2016\nApplied Languages: Japanese, English, translation, international business"
            },
            "diplomas": {
                "title": "Diplomas",
                "content": "<b>Driving license</b>　2024\n<b>Business Manner Training (OJT)</b>　2022　\n<b>Japanese Language Proficiency level 1 (JLPT N1)</b>　2019\n<b>TOEIC (score: 870)</b>　2016"
            }
        },
        "fr": {
            "title": "Profil",
            "work": {
                "title": "Parcours professional",
                "content": "<b>The Knot Tokyo Shinjuku - Vente</b>　2018-2021\nAccueil, travail en anglais et japonais, classes d'anglais, travail avec un ordinateur\n\n<b>Apro Soken - Ingénieur</b>　2021-2024\nCoding en HTML, CSS, JS / Gestion de domaine de site web / Devis pour des projets de codage"
            },
            "studies": {
                "title": "Parcours scolaire",
                "content": "<b>Étudiant en échange à l'université de Sophia - Tokyo</b>　2016-2017\nClasses de japonais intensives\n\n<b>Université Aix Marseille</b>　2013-2016\nLangues Étrangères Appliquées: japonais, anglais, traduction, business international"
            },
            "diplomas": {
                "title": "Diplômes",
                "content": "<b>Permis de conduire</b>　2024\n<b>Business Manner Training (OJT)</b>　2022　\n<b>Japanese Language Proficiency level 1 (JLPT N1)</b>　2019\n<b>TOEIC (score: 870)</b>　2016"
            }
        }
    },
    "skills": {
        "jp": {
            "title": "スキル",
            "header": {
                "title": "種類",
                "duration": "使用期間",
                "level": "レベル"
            },
            "programming": {
                "title": "プログラミング言語",
                "content": [
                    {
                        "title": "HTML / CSS",
                        "duration": "4年間",
                        "content": "問題なく使用でき、実践経験あり"
                    },
                    {
                        "title": "Javascript",
                        "duration": "4年間",
                        "content": "問題なく使用でき、実践経験あり"
                    },
                    {
                        "title": "Swift",
                        "duration": "1年間",
                        "content": "独学で学び実践できる"
                    },
                    {
                        "title": "Python",
                        "duration": "４ヶ月間",
                        "content": "独学で学び実践経験なし"
                    },
                    {
                        "title": "PHP",
                        "duration": "4年間",
                        "content": "実践経験あるが、少ししか利用していない"
                    }
                ]
            },
            "framework": {
                "title": "フレームワーク",
                "content": [
                    {
                        "title": "React",
                        "duration": "1年間",
                        "content": "実践経験あるが、少ししか利用していない"
                    },
                    {
                        "title": "jQuery",
                        "duration": "1年間",
                        "content": "利用でき、実践経験あり"
                    }
                ]
            },
            "DB": {
                "title": "DB",
                "content": [
                    {
                        "title": "mongoDB",
                        "duration": "1年",
                        "content": "独学で学び実践できる"
                    },
                    {
                        "title": "mysql",
                        "duration": "1年",
                        "content": "実践経験はあるが、少ししか利用していない"
                    }
                ]
            },
            "server": {
                "title": "サーバー",
                "content": [
                    {
                        "title": "AWS",
                        "duration": "1年",
                        "content": "実践経験はあるが、少ししか利用していない"
                    }
                ]
            },
            "cms": {
                "title": "CMS",
                "content": [
                    {
                        "title": "MovableType",
                        "duration": "3年",
                        "content": "問題なく使用でき、実践経験あり"
                    },
                    {
                        "title": "WordPress",
                        "duration": "1年",
                        "content": "実践経験あるが、少ししか利用していない"
                    }
                ]
            },
            "ecCms": {
                "title": "EC用CMS",
                "content": [
                    {
                        "title": "futureshop",
                        "duration": "3年",
                        "content": "問題なく使用でき、実践経験あり"
                    },
                    {
                        "title": "ECCube",
                        "duration": "2年",
                        "content": "使用でき、実践経験あり"
                    },
                    {
                        "title": "リピスト",
                        "duration": "2年",
                        "content": "使用でき、実践経験あり"
                    }
                ]
            },
            "software": {
                "title": "ソフトウェア",
                "content": [
                    {
                        "title": "Excel",
                        "duration": "3年",
                        "content": "使用でき、実践経験あり"
                    },
                    {
                        "title": "Photoshop",
                        "duration": "2年",
                        "content": "使用でき、実践経験あり"
                    }
                ]
            },
            "os": {
                "title": "OS",
                "content": [
                    {
                        "title": "macOS",
                        "duration": "13年間",
                        "content": "問題なく使用でき、実践経験あり"
                    },
                    {
                        "title": "Windows (10 & 11)",
                        "duration": "5年間",
                        "content": "使用でき、実践経験あり"
                    },
                    {
                        "title": "Linux (Ubuntu)",
                        "duration": "1年間",
                        "content": "独学で学び、実践経験なし"
                    }
                ]
            },
            "languages": {
                "title": "言語",
                "content": [
                    {
                        "title": "日本語",
                        "content": "８年日本在住、流暢"
                    },
                    {
                        "title": "英語",
                        "content": "流暢、検索で使用することが多い"
                    },
                    {
                        "title": "フランス語",
                        "content": "母国語"
                    }
                ]
            },
            "workskills": {
                "title": "仕事上のスキル",
                "content": [
                    {
                        "title": "フロントエンドのWEB開発経験が多い（HTML・CSS・Javascript）"
                    },
                    {
                        "title": "使ったことがない技術でも、自分で調べて行動する事が得意"
                    },
                    {
                        "title": "語学：日本語と英語とフランス語が流暢"
                    },
                    {
                        "title": "毎日の計画を立て、予想と実績に差がでないようにすることが得意"
                    },
                    {
                        "title": "ECモール（楽天、Yahoo！、Amazon…）の商品登録のような操作が可能"
                    }
                ]
            }
        },
        "en": {
            "title": "Skills",
            "header": {
                "title": "Type",
                "duration": "Duration",
                "level": "Level"
            },
            "programming": {
                "title": "Programming",
                "content": [
                    {
                        "title": "HTML / CSS",
                        "duration": "4 years",
                        "content": "For work"
                    },
                    {
                        "title": "Javascript",
                        "duration": "4 years",
                        "content": "For work"
                    },
                    {
                        "title": "Swift",
                        "duration": "1 year",
                        "content": "Currently studying, developing apps with Swift UI"
                    },
                    {
                        "title": "Python",
                        "duration": "4 months",
                        "content": "Studied"
                    },
                    {
                        "title": "PHP",
                        "duration": "4 years",
                        "content": "Some experience for work\nExperience using Smarty templates"
                    }
                ]
            },
            "framework": {
                "title": "Frameworks",
                "content": [
                    {
                        "title": "React",
                        "duration": "1 year",
                        "content": "Personal experience mainly in frontend development\nExperience with Bootstrap, Material-UI, Express"
                    },
                    {
                        "title": "jQuery",
                        "duration": "1 year",
                        "content": "Basic knowledge, prefer to use vanilla JS"
                    }
                ]
            },
            "DB": {
                "title": "Databases",
                "content": [
                    {
                        "title": "MongoDB, MySQL",
                        "duration": "1 year",
                        "content": "Studied\nSome experience with MySQL for work"
                    }
                ]
            },
            "server": {
                "title": "サーバー",
                "content": [
                    {
                        "title": "AWS",
                        "duration": "1年",
                        "content": "仕事上に使用する機会あり"
                    }
                ]
            },
            "cms": {
                "title": "CMS",
                "content": [
                    {
                        "title": "MovableType",
                        "duration": "3年",
                        "content": "問題なく日常的に利用できる"
                    },
                    {
                        "title": "WordPress",
                        "duration": "1年",
                        "content": "利用できる"
                    }
                ]
            },
            "ecCms": {
                "title": "EC用CMS",
                "content": [
                    {
                        "title": "futureshop",
                        "duration": "3年",
                        "content": "問題なく日常的に利用できる"
                    },
                    {
                        "title": "ECCube",
                        "duration": "2年",
                        "content": "利用できる"
                    },
                    {
                        "title": "リピスト",
                        "duration": "2年",
                        "content": "利用できる"
                    }
                ]
            },
            "software": {
                "title": "ソフトウェア",
                "content": [
                    {
                        "title": "Excel",
                        "duration": "3年",
                        "content": "日常的に利用できる"
                    },
                    {
                        "title": "Photoshop",
                        "duration": "2年",
                        "content": "利用できる"
                    }
                ]
            },
            "os": {
                "title": "OS",
                "content": [
                    {
                        "title": "macOS",
                        "duration": "13年間",
                        "content": "仕事上とWEB開発に使用した経験あり\n個人的に使用\nターミナルの知識あり"
                    },
                    {
                        "title": "Windows (10 & 11)",
                        "duration": "5年間",
                        "content": "仕事上とWEB開発に使用した経験あり"
                    },
                    {
                        "title": "Linux (Ubuntu)",
                        "duration": "1年間",
                        "content": "独学\nRasberry Piでサーバーとして使用した経験あり\nコマンドラインの知識あり"
                    }
                ]
            },
            "languages": {
                "title": "Languages",
                "content": [
                    {
                        "title": "Japanese",
                        "content": "Lived in Japan for 8 years, fluent"
                    },
                    {
                        "title": "English",
                        "content": "Used for searches regularly. Listen to it daily. Used in previous job."
                    },
                    {
                        "title": "French",
                        "content": "Native language"
                    }
                ]
            },
            "workskills": {
                "title": "Work Skills",
                "content": [
                    {
                        "title": "Frontend Web Development"
                    },
                    {
                        "title": "Good at self-research and taking action"
                    },
                    {
                        "title": "Other skills: Wordpress, Photoshop, .NET"
                    },
                    {
                        "title": "E-commerce: Futureshop, ECCube, Rakuten, Yahoo, Repeaters"
                    }
                ]
            }
        },
        "fr": {
            "title": "Compétences",
            "header": {
                "title": "Type",
                "duration": "Durée",
                "level": "Niveau"
            },
            "programming": {
                "title": "Programmation",
                "content": [
                    {
                        "title": "HTML / CSS",
                        "duration": "4 ans",
                        "content": "Pour le travail"
                    },
                    {
                        "title": "Javascript",
                        "duration": "4 ans",
                        "content": "Pour le travail"
                    },
                    {
                        "title": "Swift",
                        "duration": "1 an",
                        "content": "Actuellement en apprentissage, développement d'applications avec Swift UI"
                    },
                    {
                        "title": "Python",
                        "duration": "4 mois",
                        "content": "Étudié"
                    },
                    {
                        "title": "PHP",
                        "duration": "4 ans",
                        "content": "Quelques expériences pour le travail\nExpérience avec les modèles Smarty"
                    }
                ]
            },
            "framework": {
                "title": "Frameworks",
                "content": [
                    {
                        "title": "React",
                        "duration": "1 an",
                        "content": "Expérience personnelle principalement en développement front end\nExpérience avec Bootstrap, Material-UI, Express"
                    },
                    {
                        "title": "jQuery",
                        "duration": "1 an",
                        "content": "Connaissances, préfère utiliser JS pur"
                    }
                ]
            },
            "DB": {
                "title": "Bases de données",
                "content": [
                    {
                        "title": "MongoDB, MySQL",
                        "duration": "1 an",
                        "content": "Étudié\nQuelques expériences avec MySQL pour le travail"
                    }
                ]
            },
            "server": {
                "title": "サーバー",
                "content": [
                    {
                        "title": "AWS",
                        "duration": "1年",
                        "content": "仕事上に使用する機会あり"
                    }
                ]
            },
            "cms": {
                "title": "CMS",
                "content": [
                    {
                        "title": "MovableType",
                        "duration": "3年",
                        "content": "問題なく日常的に利用できる"
                    },
                    {
                        "title": "WordPress",
                        "duration": "1年",
                        "content": "利用できる"
                    }
                ]
            },
            "ecCms": {
                "title": "EC用CMS",
                "content": [
                    {
                        "title": "futureshop",
                        "duration": "3年",
                        "content": "問題なく日常的に利用できる"
                    },
                    {
                        "title": "ECCube",
                        "duration": "2年",
                        "content": "利用できる"
                    },
                    {
                        "title": "リピスト",
                        "duration": "2年",
                        "content": "利用できる"
                    }
                ]
            },
            "software": {
                "title": "ソフトウェア",
                "content": [
                    {
                        "title": "Excel",
                        "duration": "3年",
                        "content": "日常的に利用できる"
                    },
                    {
                        "title": "Photoshop",
                        "duration": "2年",
                        "content": "利用できる"
                    }
                ]
            },
            "os": {
                "title": "OS",
                "content": [
                    {
                        "title": "macOS",
                        "duration": "13年間",
                        "content": "仕事上とWEB開発に使用した経験あり\n個人的に使用\nターミナルの知識あり"
                    },
                    {
                        "title": "Windows (10 & 11)",
                        "duration": "5年間",
                        "content": "仕事上とWEB開発に使用した経験あり"
                    },
                    {
                        "title": "Linux (Ubuntu)",
                        "duration": "1年間",
                        "content": "独学\nRasberry Piでサーバーとして使用した経験あり\nコマンドラインの知識あり"
                    }
                ]
            },
            "languages": {
                "title": "Langues",
                "content": [
                    {
                        "title": "Japonais",
                        "content": "Vécu au Japon pendant 8 ans, fluent"
                    },
                    {
                        "title": "Anglais",
                        "content": "Utilisé régulièrement pour les recherches. Écoute quotidienne. Utilisé dans un emploi précédent."
                    },
                    {
                        "title": "Français",
                        "content": "Langue maternelle"
                    }
                ]
            },
            "workskills": {
                "title": "Compétences professionnelles",
                "content": [
                    {
                        "title": "Développement web frontend"
                    },
                    {
                        "title": "Bonne capacité à rechercher et à agir de manière autonome"
                    },
                    {
                        "title": "Autres compétences : Wordpress, Photoshop, .NET"
                    },
                    {
                        "title": "E-commerce : Futureshop, ECCube, Rakuten, Yahoo, Repeaters"
                    }
                ]
            }
        }
    },
    "apps": {
        "jp": {
            "title": "実績",
            "appGroups": {
                "portfolio": {
                    "title": "ポートフォリオ作成",
                    "description": "当ポートフォリオをReactでコーディング　　サーバー：Github Pages　　使用プラグイン：react-router-dom・framer-motion"
                },
                "iosApps": {
                    "title": "iOS Apps",
                    "content": {
                        "dayPlan": {
                            "title": "Day Plan",
                            "description": "一日のスケジュールを簡単に入力・レビューするためのアプリを開発中　　個人で他アプリを使用した時、入力にかなり時間がかかるという問題から、このアプリの売りとしてタスク追加をできるだけシンプルに　　カレンダーのイベントと連携、iCloudバックアップの２機能が出来次第公開予定"
                        }
                    }
                },
                "iosTrainingApps": {
                    "title": "練習用のiOSアプリ開発",
                    "description": "こちらはオンラインコースで作成した練習用の公開予定ではないiOSアプリ一覧",
                    "content": {
                        "flashChat": {
                            "title": "Flash Chat",
                            "description": "Firebase DBを使用したチャットアプリ　　アカウント作成、ログイン、チャットメッセージを送信できる機能"
                        },
                        "todo": {
                            "title": "Todo",
                            "description": "リマインダーとリマインダーグループ作成が可能"
                        },
                        "bmiCalculator": {
                            "title": "BMI Calculator",
                            "description": "体重と身長を入力しBMIが計算できるアプリ"
                        },
                        "calculator": {
                            "title": "Calculator",
                            "description": "+ - × ÷ の電卓機能ができるアプリ"
                        },
                        "dicee": {
                            "title": "Dicee",
                            "description": "２つのサイコロを再現するアプリ"
                        },
                        "divide": {
                            "title": "Divide",
                            "description": "割り算のためのアプリ"
                        },
                        "hackerNews": {
                            "title": "Hacker News",
                            "description": "Hacker NewsのAPIを使用しニュースを閲覧できるアプリ"
                        },
                        "itemFinder": {
                            "title": "Item Finder",
                            "description": "アップルの機械技術（Core ML）を使用した、写真で撮ったものを認識できるアプリ"
                        }
                    }
                },
                "ecSitesCoding": {
                    "title": "ECサイトのコーディング",
                    "description": "HTML・CSS・Javascriptを使用し、FutureshopというEC用のCMS上、約20のSP用のアクセサリー販売サイトを作成"
                },
                "excelProjects": {
                    "title": "ExcelのCSV変換ツール",
                    "description": "複数EC用CMSやモールに商品できるよう、Excelの関数やマクロを使用したCSV変換ツールを作成"
                },
                "reactProjects": {
                    "title": "Reactアプリ",
                    "colorPicker": {
                        "title": "Color Picker",
                        "description": "カラーパレットを作成できるWebアプリ（スクリーンショットをクリックするとアプリが表示される）"
                    },
                    "moneySaver": {
                        "title": "Money Saver",
                        "description": "個人の支出入力・管理Webアプリ（現在使用不可）"
                    }
                }
            }
        },
        "en": {
            "title": "Achievements",
            "appGroups": {
                "portfolio": {
                    "title": "Coding of this portfolio",
                    "description": "Server：Github Pages　　Plugin：react-router-dom・framer-motion"
                },
                "iosApps": {
                    "title": "iOS Apps",
                    "content": {
                        "dayPlan": {
                            "title": "Day Plan",
                            "description": "Developing an app for easily inputting and reviewing daily schedules. The advantage of this app is that tasks can be added as simply and quickly as possible. Most of the development is done. The app will be released once calendar event integration and iCloud backup features are complete."
                        }
                    }
                },
                "iosTrainingApps": {
                    "title": "iOS Training Apps",
                    "description": "These are practice iOS apps created in an online course that are not intended for public release",
                    "content": {
                        "flashChat": {
                            "title": "Flash Chat",
                            "description": "A chat app using Firebase DB. Features include account creation, login, and sending chat messages."
                        },
                        "todo": {
                            "title": "Todo",
                            "description": "Allows creation of reminders and reminder groups."
                        },
                        "bmiCalculator": {
                            "title": "BMI Calculator",
                            "description": "An app to calculate BMI by inputting weight and height."
                        },
                        "calculator": {
                            "title": "Calculator",
                            "description": "An app that can perform + - × ÷ calculations."
                        },
                        "dicee": {
                            "title": "Dicee",
                            "description": "An app that simulates two dice."
                        },
                        "divide": {
                            "title": "Divide",
                            "description": "An app for division calculations."
                        },
                        "hackerNews": {
                            "title": "Hacker News",
                            "description": "An app that uses the Hacker News API to view news."
                        },
                        "itemFinder": {
                            "title": "Item Finder",
                            "description": "An app that uses Apple's Core ML to recognize items in photos."
                        }
                    }
                },
                "ecSitesCoding": {
                    "title": "EC Site Coding",
                    "description": "Created about 20 accessory sales sites for mobile using HTML, CSS, and Javascript on the Futureshop CMS for e-commerce."
                },
                "excelProjects": {
                    "title": "Excel CSV Conversion Tool",
                    "description": "Created a CSV conversion tool using Excel functions and macros."
                },
                "reactProjects": {
                    "title": "React Apps",
                    "colorPicker": {
                        "title": "Color Picker",
                        "description": "A web app for creating color palettes."
                    },
                    "moneySaver": {
                        "title": "Money Saver",
                        "description": "A web app for personal expense input and management."
                    }
                }
            }
        },
        "fr": {
            "title": "Réalisations",
            "appGroups": {
                "portfolio": {
                    "title": "Coding de ce portfolio",
                    "description": "Serveur：Github Pages　　Plugin：react-router-dom・framer-motion"
                },
                "iosApps": {
                    "title": "Applications iOS",
                    "content": {
                        "dayPlan": {
                            "title": "Plan de Jour",
                            "description": "Développement d'une application pour saisir et revoir facilement les emplois du temps quotidiens. L'avantage de cette application est que les tâches peuvent être ajoutées aussi simplement et rapidement que possible. La majeure partie du développement est terminée. L'application sera publiée une fois les fonctionnalités d'intégration des événements du calendrier et de sauvegarde iCloud terminées."
                        }
                    }
                },
                "iosTrainingApps": {
                    "title": "Applications d'Entraînement iOS",
                    "description": "Il s'agit d'applications iOS de pratique créées dans un cours en ligne qui ne sont pas destinées à être publiées",
                    "content": {
                        "flashChat": {
                            "title": "Flash Chat",
                            "description": "Une application de chat utilisant Firebase DB. Les fonctionnalités incluent la création de comptes, la connexion et l'envoi de messages de chat."
                        },
                        "todo": {
                            "title": "Todo",
                            "description": "Permet la création de rappels et de groupes de rappels."
                        },
                        "bmiCalculator": {
                            "title": "Calculateur d'IMC",
                            "description": "Une application pour calculer l'IMC en saisissant le poids et la taille."
                        },
                        "calculator": {
                            "title": "Calculatrice",
                            "description": "Une application pouvant effectuer des calculs + - × ÷."
                        },
                        "dicee": {
                            "title": "Dicee",
                            "description": "Une application simulant deux dés."
                        },
                        "divide": {
                            "title": "Diviser",
                            "description": "Une application pour les calculs de division."
                        },
                        "hackerNews": {
                            "title": "Hacker News",
                            "description": "Une application utilisant l'API Hacker News pour consulter les nouvelles."
                        },
                        "itemFinder": {
                            "title": "Trouveur d'Objets",
                            "description": "Une application utilisant le Core ML d'Apple pour reconnaître les objets dans les photos."
                        }
                    }
                },
                "ecSitesCoding": {
                    "title": "Codage de Sites EC",
                    "description": "Création d'environ 20 sites de vente d'accessoires pour mobile en utilisant HTML, CSS et Javascript sur le CMS Futureshop pour le commerce électronique."
                },
                "excelProjects": {
                    "title": "Outil de Conversion CSV pour Excel",
                    "description": "Création d'un outil de conversion CSV utilisant les fonctions et macros d'Excel."
                },
                "reactProjects": {
                    "title": "Applications React",
                    "colorPicker": {
                        "title": "Sélecteur de Couleurs",
                        "description": "Une application web pour créer des palettes de couleurs."
                    },
                    "moneySaver": {
                        "title": "Économiseur d'Argent",
                        "description": "Une application web pour la saisie et la gestion des dépenses personnelles."
                    }
                }
            }
        }        
    }
}